{
  "questions": [
    {
      "question_desc": "get player's name",
      "question_id": "00",
      "expression_weight": 0,
      "consistency_weight": 1,
      "no_of_variations": 2,
      "considers_emotion": false,
      "considers_fact": true,
      "variations": [
        {
          "question_text": "Please state your full name for the record.",
          "variation_no": 1,
          "answers": [
            {
              "answer_id": "000",
              "answer_text": "Christine  Tse"
            },
            {
              "answer_id": "001",
              "answer_text": "Eugene Cheong"
            },
            {
              "answer_id": "002",
              "answer_text": "Felicia Agatha"
            },
            {
              "answer_id": "003",
              "answer_text": "Vivian Rajkumar"
            }
          ]
        },
        {
          "question_text": "What is your name?",
          "variation_no": 2,
          "answers": [
            {
              "answer_id": "000",
              "answer_text": "Christine  Tse"
            },
            {
              "answer_id": "001",
              "answer_text": "Eugene Cheong"
            },
            {
              "answer_id": "002",
              "answer_text": "Felicia Agatha"
            },
            {
              "answer_id": "003",
              "answer_text": "Vivian Rajkumar"
            }
          ]
        }
      ]
    },
    {
      "question_desc": "get player's age",
      "question_id": "01",
      "expression_weight": 0,
      "consistency_weight": 1,
      "no_of_variations": 2,
      "considers_emotion": false,
      "considers_fact": true,
      "variations": [
        {
          "question_text": "Please state your age for the record.",
          "variation_no": 1,
          "answers": [
            {
              "answer_id": "010",
              "answer_text": "18"
            },
            {
              "answer_id": "011",
              "answer_text": "26"
            },
            {
              "answer_id": "012",
              "answer_text": "30"
            },
            {
              "answer_id": "013",
              "answer_text": "45"
            }
          ]
        },
        {
          "question_text": "How old are you?",
          "variation_no": 2,
          "answers": [
            {
              "answer_id": "010",
              "answer_text": "18"
            },
            {
              "answer_id": "011",
              "answer_text": "26"
            },
            {
              "answer_id": "012",
              "answer_text": "30"
            },
            {
              "answer_id": "013",
              "answer_text": "45"
            }
          ]
        }
      ]
    },
    {
      "question_desc": "ask how player is feeling",
      "question_id": "02",
      "expression_weight": 1,
      "consistency_weight": 0,
      "no_of_variations": 2,
      "considers_emotion": true,
      "considers_fact": true,
      "variations": [
        {
          "question_text": "How are you feeling today?",
          "variation_no": 1,
          "answers": [
            {
              "answer_id": "020",
              "answer_text": "Great!",
              "expected_expression": [
                "happy"
              ],
              "detective_response": "positive"
            },
            {
              "answer_id": "021",
              "answer_text": "Alright",
              "expected_expression": [
                "neutral"
              ],
              "detective_response": "unsure"
            },
            {
              "answer_id": "022",
              "answer_text": "Teribble!",
              "expected_expression": [
                "anger",
                "sad"
              ],
              "detective_response": "negative"
            },
            {
              "answer_id": "023",
              "answer_text": "I'm scared!",
              "expected_expression": [
                "fear",
                "surprised"
              ],
              "detective_response": "negative"
            }
          ]
        },
        {
          "question_text": "How are you doing?",
          "variation_no": 2,
          "answers": [
            {
              "answer_id": "020",
              "answer_text": "Great!",
              "expected_expression": [
                "happy"
              ],
              "detective_response": "positive"
            },
            {
              "answer_id": "021",
              "answer_text": "Alright",
              "expected_expression": [
                "neutral"
              ],
              "detective_response": "unsure"
            },
            {
              "answer_id": "022",
              "answer_text": "Teribble!",
              "expected_expression": [
                "anger",
                "sad"
              ],
              "detective_response": "negative"
            },
            {
              "answer_id": "023",
              "answer_text": "I'm scared!",
              "expected_expression": [
                "fear",
                "surprised"
              ],
              "detective_response": "negative"
            }
          ]
        }
      ]
    }
  ]
}